setup.py
distributions/Binomialdistribution.py
distributions/Gaussiandistribution.py
distributions/Generaldistribution.py
distributions/__init__.py
dsdn_distributions_rmis.egg-info/PKG-INFO
dsdn_distributions_rmis.egg-info/SOURCES.txt
dsdn_distributions_rmis.egg-info/dependency_links.txt
dsdn_distributions_rmis.egg-info/not-zip-safe
dsdn_distributions_rmis.egg-info/top_level.txt